byte_blaster-1.0.0.dist-info/licenses/LICENSE
byteblaster/__init__.py
byteblaster/client.py
byteblaster/file_manager.py
byteblaster/handler.py
byteblaster/py.typed
byteblaster/protocol/__init__.py
byteblaster/protocol/auth.py
byteblaster/protocol/decoder.py
byteblaster/protocol/models.py
byteblaster/utils/__init__.py
byteblaster/utils/crypto.py
byteblaster/utils/serverlist.py
byte_blaster-1.0.0.dist-info/METADATA
byte_blaster-1.0.0.dist-info/WHEEL
byte_blaster-1.0.0.dist-info/top_level.txt
byte_blaster-1.0.0.dist-info/RECORD
